Workbook

Sheet Сводка
B2: СВОДКА ЗАКАЗА — рентабельность и цена КП
B3: Сначала заполните Металл и Калькуляцию. Жёлтое — ввод. Остальное считается автоматически.
B5: ШАПКА ЗАКАЗА | E5: ПАРАМЕТРЫ (зеркало)
B6: Объект | E6: Наценка менеджера | F6: ='Параметры'!C6
B7: Конструкция / изделие | E7: Целевая маржа | F7: ='Параметры'!C7
B8: Тип | E8: Мин. маржа | F8: ='Параметры'!C8
B9: Дата расчёта | C9: =TODAY() | E9: НПД | F9: ='Параметры'!C9
B10: Клиент | E10: Аренда / день | F10: ='Параметры'!C10
B11: № клиента | E11: Агентские | F11: ='Параметры'!C12
B13: P&L ПРОЕКТА
B14: Себестоимость проекта (реальные затраты) | D14: ='Калькуляция'!O8
B15: в т.ч. закупки у поставщиков | D15: ='Калькуляция'!O9
B16: в т.ч. труд | D16: ='Калькуляция'!O10
B17: в т.ч. транспорт | D17: ='Калькуляция'!O11
B18: в т.ч. аренда цеха | D18: ='Калькуляция'!O12
B19: в т.ч. услуги / прочее | D19: ='Калькуляция'!O13
B20: Наценка менеджера на закупки (часть прибыли) | D20: ='Калькуляция'!O14
B21: Дни цеха (по строкам аренды) | D21: ='Калькуляция'!O15
B23: ЦЕНА И МАРЖА
B24: Цена КП (то, что выставите клиенту) | D24: 337000
B25: Рекомендуемая цена при целевой марже | D25: =IF((1-F9-F7-F11)<=0,"Ошибка %",D14/(1-F9-F7-F11))
B26: Минимальная цена (при мин. марже) | D26: =IF((1-F9-F8-F11)<=0,"Ошибка %",D14/(1-F9-F8-F11))
B27: НПД с цены КП | D27: =D24*F9
B28: Агентские с цены КП | D28: =D24*F11
B29: Чистая прибыль при цене КП | D29: =D24-D14-D27-D28
B30: Маржа % при цене КП (от выручки) | D30: =IF(D24=0,0,D29/D24)
B31: Статус | D31: =IF(D24=0,"Введите цену КП",IF(D30<F8,"НИЖЕ МИНИМУМА",IF(D30<F7,"НИЖЕ ЦЕЛИ","ЦЕЛЬ ДОСТИГНУТА")))
B33: ГИБКАЯ МАРЖА — таблица цен
B34: Целевая маржа | C34: Цена КП | D34: НПД | E34: Прибыль
B35: 0.1 | C35: =IF((1-$F$9-B35-$F$11)<=0,0,$D$14/(1-$F$9-B35-$F$11)) | D35: =C35*$F$9 | E35: =C35-$D$14-D35-C35*$F$11
B36: 0.15 | C36: =IF((1-$F$9-B36-$F$11)<=0,0,$D$14/(1-$F$9-B36-$F$11)) | D36: =C36*$F$9 | E36: =C36-$D$14-D36-C36*$F$11
B37: 0.2 | C37: =IF((1-$F$9-B37-$F$11)<=0,0,$D$14/(1-$F$9-B37-$F$11)) | D37: =C37*$F$9 | E37: =C37-$D$14-D37-C37*$F$11
B38: 0.25 | C38: =IF((1-$F$9-B38-$F$11)<=0,0,$D$14/(1-$F$9-B38-$F$11)) | D38: =C38*$F$9 | E38: =C38-$D$14-D38-C38*$F$11
B39: 0.3 | C39: =IF((1-$F$9-B39-$F$11)<=0,0,$D$14/(1-$F$9-B39-$F$11)) | D39: =C39*$F$9 | E39: =C39-$D$14-D39-C39*$F$11
B40: 0.35 | C40: =IF((1-$F$9-B40-$F$11)<=0,0,$D$14/(1-$F$9-B40-$F$11)) | D40: =C40*$F$9 | E40: =C40-$D$14-D40-C40*$F$11
B42: Строка 20% — базовый ориентир. Целевую маржу меняйте на листе Параметры.
B44: КОНТРОЛЬ
B45: Доля наценки менеджера в прибыли (при цене КП) | D45: =IF(D29<=0,0,D20/D29)
B46: Выручка на день цеха | D46: =IF(D21=0,0,D24/D21)
B47: Прибыль на день цеха | D47: =IF(D21=0,0,D29/D21)
B49: Рабочий контур: Металл → Калькуляция → Сводка (цена КП). Лист «Касса» — только ПОСЛЕ сделки, для авансов/выплат. На расчёт цены НЕ влияет — можно не трогать.

Sheet Калькуляция
B2: КАЛЬКУЛЯЦИЯ ПРОЕКТА
B3: Жёлтые — ввод. Тип «закупка» получает наценку менеджера из Параметров. Аренда подтягивает ставку/день. Итоги справа — для Сводки.
B5: Этап | C5: Статья / обоснование | D5: Тип | E5: Цена / ставка | F5: Кол-во | G5: Ед. | H5: Себестоимость | I5: Наценка менеджера | J5: В базу КП | L5: Примечание | N5: ИТОГИ ДЛЯ СВОДКИ
B6: 1. Проектирование / замер | N6: Контроль суммы себест. | O6: =SUM(H6:H250)
B7: Проектирование | C7: Аренда на замер | D7: аренда | E7: ='Параметры'!$C$10 | F7: 0 | G7: день | H7: =IF(OR(E7="",F7=""),0,E7*F7) | I7: =IF(D7="закупка",H7*'Параметры'!$C$6,0) | J7: =H7+I7 | L7: Ставка аренды из Параметры | N7: Контроль наценки менеджера | O7: =SUM(I6:I250)
B8: Проектирование | C8: Транспорт по городу | D8: транспорт | E8: 2000 | F8: 0 | G8: выезд | H8: =IF(OR(E8="",F8=""),0,E8*F8) | I8: =IF(D8="закупка",H8*'Параметры'!$C$6,0) | J8: =H8+I8 | N8: Себестоимость проекта | O8: =O6
B9: Проектирование | C9: Транспорт по области | D9: транспорт | E9: 4000 | F9: 0 | G9: выезд | H9: =IF(OR(E9="",F9=""),0,E9*F9) | I9: =IF(D9="закупка",H9*'Параметры'!$C$6,0) | J9: =H9+I9 | N9: Закупки | O9: =SUMIF(D6:D250,"закупка",H6:H250)
B10: Проектирование | C10: Замер | D10: услуга | E10: 6000 | F10: 0 | G10: услуга | H10: =IF(OR(E10="",F10=""),0,E10*F10) | I10: =IF(D10="закупка",H10*'Параметры'!$C$6,0) | J10: =H10+I10 | N10: Труд | O10: =SUMIF(D6:D250,"труд",H6:H250)
B11: Проектирование | C11: Консультация | D11: услуга | E11: 6000 | F11: 0 | G11: услуга | H11: =IF(OR(E11="",F11=""),0,E11*F11) | I11: =IF(D11="закупка",H11*'Параметры'!$C$6,0) | J11: =H11+I11 | N11: Транспорт | O11: =SUMIF(D6:D250,"транспорт",H6:H250)
B12: Проектирование | C12: Проектирование, эскизы | D12: услуга | E12: 13000 | F12: 0 | G12: услуга | H12: =IF(OR(E12="",F12=""),0,E12*F12) | I12: =IF(D12="закупка",H12*'Параметры'!$C$6,0) | J12: =H12+I12 | N12: Аренда | O12: =SUMIF(D6:D250,"аренда",H6:H250)
B13: 2. Снять лекала / подготовка | N13: Услуги/прочее | O13: =O6-O9-O10-O11-O12
B14: Лекала | C14: Аренда | D14: аренда | E14: ='Параметры'!$C$10 | F14: 0 | G14: день | H14: =IF(OR(E14="",F14=""),0,E14*F14) | I14: =IF(D14="закупка",H14*'Параметры'!$C$6,0) | J14: =H14+I14 | L14: Ставка аренды из Параметры | N14: Наценка менеджера | O14: =O7
B15: Лекала | C15: Мастер | D15: труд | E15: 7000 | G15: день | H15: =IF(OR(E15="",F15=""),0,E15*F15) | I15: =IF(D15="закупка",H15*'Параметры'!$C$6,0) | J15: =H15+I15 | N15: Дни цеха | O15: =SUMIF(D6:D250,"аренда",F6:F250)
B16: Лекала | C16: Рабочий | D16: труд | E16: 5000 | F16: 0 | G16: день | H16: =IF(OR(E16="",F16=""),0,E16*F16) | I16: =IF(D16="закупка",H16*'Параметры'!$C$6,0) | J16: =H16+I16
B17: Лекала | C17: Транспорт цех → объект | D17: транспорт | E17: 2000 | F17: 0 | G17: рейс | H17: =IF(OR(E17="",F17=""),0,E17*F17) | I17: =IF(D17="закупка",H17*'Параметры'!$C$6,0) | J17: =H17+I17
B18: Лекала | C18: Транспорт объект → цех | D18: транспорт | E18: 2000 | F18: 0 | G18: рейс | H18: =IF(OR(E18="",F18=""),0,E18*F18) | I18: =IF(D18="закупка",H18*'Параметры'!$C$6,0) | J18: =H18+I18
B19: Лекала | C19: Картоны | D19: закупка | E19: 300 | F19: 0 | G19: шт | H19: =IF(OR(E19="",F19=""),0,E19*F19) | I19: =IF(D19="закупка",H19*'Параметры'!$C$6,0) | J19: =H19+I19
B20: Лекала | C20: Расходники | D20: закупка | E20: 250 | F20: 0 | G20: набор | H20: =IF(OR(E20="",F20=""),0,E20*F20) | I20: =IF(D20="закупка",H20*'Параметры'!$C$6,0) | J20: =H20+I20
B21: Лекала | C21: Дерево | D21: закупка | E21: 1500 | F21: 0 | G21: набор | H21: =IF(OR(E21="",F21=""),0,E21*F21) | I21: =IF(D21="закупка",H21*'Параметры'!$C$6,0) | J21: =H21+I21
B22: 3. Закуп металла
B23: Металл | C23: Транспорт: микроавтобус (2ч) | D23: транспорт | E23: 2000 | G23: рейс | H23: =IF(OR(E23="",F23=""),0,E23*F23) | I23: =IF(D23="закупка",H23*'Параметры'!$C$6,0) | J23: =H23+I23
B24: Металл | C24: Транспорт: бортовая 4м (1ч) | D24: транспорт | E24: 1500 | G24: рейс | H24: =IF(OR(E24="",F24=""),0,E24*F24) | I24: =IF(D24="закупка",H24*'Параметры'!$C$6,0) | J24: =H24+I24
B25: Металл | C25: Транспорт: бортовая 6м (1ч) | D25: транспорт | E25: 3500 | G25: рейс | H25: =IF(OR(E25="",F25=""),0,E25*F25) | I25: =IF(D25="закупка",H25*'Параметры'!$C$6,0) | J25: =H25+I25
B26: Металл | C26: Металлопрокат (лист Металл) | D26: закупка | E26: ='Металл'!H37 | G26: сводка | H26: =IF(OR(E26="",F26=""),0,E26*F26) | I26: =IF(D26="закупка",H26*'Параметры'!$C$6,0) | J26: =H26+I26 | L26: Себестоимость проката (каталог, цена за шт 6м)
B27: Металл | C27: Лазер / плазма (лист Металл) | D27: закупка | E27: ='Металл'!H52 | G27: сводка | H27: =IF(OR(E27="",F27=""),0,E27*F27) | I27: =IF(D27="закупка",H27*'Параметры'!$C$6,0) | J27: =H27+I27
B28: Металл | C28: Ков. элементы / спец. прокат | D28: закупка | E28: ='Металл'!H67 | G28: сводка | H28: =IF(OR(E28="",F28=""),0,E28*F28) | I28: =IF(D28="закупка",H28*'Параметры'!$C$6,0) | J28: =H28+I28
B29: Металл | C29: Токарные работы (лист Металл) | D29: закупка | E29: ='Металл'!H82 | G29: сводка | H29: =IF(OR(E29="",F29=""),0,E29*F29) | I29: =IF(D29="закупка",H29*'Параметры'!$C$6,0) | J29: =H29+I29
B30: Металл | C30: Доп. комплектующие (лист Металл) | D30: закупка | E30: ='Металл'!H97 | G30: сводка | H30: =IF(OR(E30="",F30=""),0,E30*F30) | I30: =IF(D30="закупка",H30*'Параметры'!$C$6,0) | J30: =H30+I30
B31: 4. Производство
B32: Производство | C32: Аренда цеха | D32: аренда | E32: ='Параметры'!$C$10 | G32: день | H32: =IF(OR(E32="",F32=""),0,E32*F32) | I32: =IF(D32="закупка",H32*'Параметры'!$C$6,0) | J32: =H32+I32 | L32: Ставка аренды из Параметры
B33: Производство | C33: Оплата труда: мастер | D33: труд | E33: 6000 | G33: день | H33: =IF(OR(E33="",F33=""),0,E33*F33) | I33: =IF(D33="закупка",H33*'Параметры'!$C$6,0) | J33: =H33+I33 | L33: ФИО в примечании
B34: Производство | C34: Оплата труда: рабочий | D34: труд | E34: 4000 | G34: день | H34: =IF(OR(E34="",F34=""),0,E34*F34) | I34: =IF(D34="закупка",H34*'Параметры'!$C$6,0) | J34: =H34+I34
B35: Производство | C35: Оплата труда: доп.1 | D35: труд | E35: 6000 | G35: день | H35: =IF(OR(E35="",F35=""),0,E35*F35) | I35: =IF(D35="закупка",H35*'Параметры'!$C$6,0) | J35: =H35+I35
B36: Производство | C36: Оплата труда: доп.2 | D36: труд | E36: 4000 | G36: день | H36: =IF(OR(E36="",F36=""),0,E36*F36) | I36: =IF(D36="закупка",H36*'Параметры'!$C$6,0) | J36: =H36+I36
B37: 5. Предмонтаж
B38: Предмонтаж | C38: Аренда | D38: аренда | E38: ='Параметры'!$C$10 | G38: день | H38: =IF(OR(E38="",F38=""),0,E38*F38) | I38: =IF(D38="закупка",H38*'Параметры'!$C$6,0) | J38: =H38+I38 | L38: Ставка аренды из Параметры
B39: Предмонтаж | C39: Монтажники | D39: труд | E39: 7300 | F39: 0 | G39: день | H39: =IF(OR(E39="",F39=""),0,E39*F39) | I39: =IF(D39="закупка",H39*'Параметры'!$C$6,0) | J39: =H39+I39
B40: Предмонтаж | C40: Помощник | D40: труд | E40: 5000 | F40: 0 | G40: день | H40: =IF(OR(E40="",F40=""),0,E40*F40) | I40: =IF(D40="закупка",H40*'Параметры'!$C$6,0) | J40: =H40+I40
B41: Предмонтаж | C41: Транспорт цех → объект | D41: транспорт | E41: 2000 | F41: 0 | G41: рейс | H41: =IF(OR(E41="",F41=""),0,E41*F41) | I41: =IF(D41="закупка",H41*'Параметры'!$C$6,0) | J41: =H41+I41
B42: Предмонтаж | C42: Транспорт объект → цех | D42: транспорт | E42: 2000 | F42: 0 | G42: рейс | H42: =IF(OR(E42="",F42=""),0,E42*F42) | I42: =IF(D42="закупка",H42*'Параметры'!$C$6,0) | J42: =H42+I42
B43: Предмонтаж | C43: Такси | D43: транспорт | E43: 1500 | F43: 0 | G43: поездка | H43: =IF(OR(E43="",F43=""),0,E43*F43) | I43: =IF(D43="закупка",H43*'Параметры'!$C$6,0) | J43: =H43+I43
B44: 6. Покраска эмалью
B45: Покраска эмаль | C45: Аренда | D45: аренда | E45: ='Параметры'!$C$10 | F45: 0 | G45: день | H45: =IF(OR(E45="",F45=""),0,E45*F45) | I45: =IF(D45="закупка",H45*'Параметры'!$C$6,0) | J45: =H45+I45 | L45: Ставка аренды из Параметры
B46: Покраска эмаль | C46: Маляр | D46: труд | E46: 3000 | F46: 0 | G46: день | H46: =IF(OR(E46="",F46=""),0,E46*F46) | I46: =IF(D46="закупка",H46*'Параметры'!$C$6,0) | J46: =H46+I46
B47: Покраска эмаль | C47: Рабочий | D47: труд | E47: 5000 | F47: 0 | G47: день | H47: =IF(OR(E47="",F47=""),0,E47*F47) | I47: =IF(D47="закупка",H47*'Параметры'!$C$6,0) | J47: =H47+I47
B48: Покраска эмаль | C48: Респиратор | D48: закупка | E48: 500 | F48: 0 | G48: шт | H48: =IF(OR(E48="",F48=""),0,E48*F48) | I48: =IF(D48="закупка",H48*'Параметры'!$C$6,0) | J48: =H48+I48
B49: Покраска эмаль | C49: Грунт | D49: закупка | E49: 600 | F49: 0 | G49: шт | H49: =IF(OR(E49="",F49=""),0,E49*F49) | I49: =IF(D49="закупка",H49*'Параметры'!$C$6,0) | J49: =H49+I49
B50: Покраска эмаль | C50: Лак | D50: закупка | E50: 1000 | F50: 0 | G50: шт | H50: =IF(OR(E50="",F50=""),0,E50*F50) | I50: =IF(D50="закупка",H50*'Параметры'!$C$6,0) | J50: =H50+I50
B51: Покраска эмаль | C51: Эмаль 0,8л | D51: закупка | E51: 1200 | F51: 0 | G51: шт | H51: =IF(OR(E51="",F51=""),0,E51*F51) | I51: =IF(D51="закупка",H51*'Параметры'!$C$6,0) | J51: =H51+I51
B52: Покраска эмаль | C52: Эмаль 2,0л | D52: закупка | E52: 3500 | F52: 0 | G52: шт | H52: =IF(OR(E52="",F52=""),0,E52*F52) | I52: =IF(D52="закупка",H52*'Параметры'!$C$6,0) | J52: =H52+I52
B53: Покраска эмаль | C53: Мет.щётки, кисти | D53: закупка | E53: 300 | F53: 0 | G53: набор | H53: =IF(OR(E53="",F53=""),0,E53*F53) | I53: =IF(D53="закупка",H53*'Параметры'!$C$6,0) | J53: =H53+I53
B54: Покраска эмаль | C54: Растворитель | D54: закупка | E54: 370 | F54: 0 | G54: шт | H54: =IF(OR(E54="",F54=""),0,E54*F54) | I54: =IF(D54="закупка",H54*'Параметры'!$C$6,0) | J54: =H54+I54
B55: Покраска эмаль | C55: Холодный цинк | D55: закупка | E55: 2500 | F55: 0 | G55: шт | H55: =IF(OR(E55="",F55=""),0,E55*F55) | I55: =IF(D55="закупка",H55*'Параметры'!$C$6,0) | J55: =H55+I55
B56: Покраска эмаль | C56: Транспорт микроавтобус | D56: транспорт | E56: 2000 | F56: 0 | G56: рейс | H56: =IF(OR(E56="",F56=""),0,E56*F56) | I56: =IF(D56="закупка",H56*'Параметры'!$C$6,0) | J56: =H56+I56
B57: Покраска эмаль | C57: Транспорт бортовая 4м | D57: транспорт | E57: 1500 | F57: 0 | G57: рейс | H57: =IF(OR(E57="",F57=""),0,E57*F57) | I57: =IF(D57="закупка",H57*'Параметры'!$C$6,0) | J57: =H57+I57
B58: Покраска эмаль | C58: Транспорт бортовая 6м | D58: транспорт | E58: 3500 | F58: 0 | G58: рейс | H58: =IF(OR(E58="",F58=""),0,E58*F58) | I58: =IF(D58="закупка",H58*'Параметры'!$C$6,0) | J58: =H58+I58
B59: 7. Пескоструй
B60: Пескоструй | C60: Услуга пескоструй | D60: услуга | E60: 900 | F60: 0 | G60: м | H60: =IF(OR(E60="",F60=""),0,E60*F60) | I60: =IF(D60="закупка",H60*'Параметры'!$C$6,0) | J60: =H60+I60
B61: Пескоструй | C61: Транспорт на пескоструй | D61: транспорт | E61: 2000 | F61: 0 | G61: рейс | H61: =IF(OR(E61="",F61=""),0,E61*F61) | I61: =IF(D61="закупка",H61*'Параметры'!$C$6,0) | J61: =H61+I61
B62: Пескоструй | C62: Транспорт с пескоструя | D62: транспорт | E62: 2000 | F62: 0 | G62: рейс | H62: =IF(OR(E62="",F62=""),0,E62*F62) | I62: =IF(D62="закупка",H62*'Параметры'!$C$6,0) | J62: =H62+I62
B63: 8. Порошковая покраска
B64: Порошок | C64: Покраска обычная | D64: услуга | E64: 2000 | G64: услуга | H64: =IF(OR(E64="",F64=""),0,E64*F64) | I64: =IF(D64="закупка",H64*'Параметры'!$C$6,0) | J64: =H64+I64
B65: Порошок | C65: Покраска с цинком | D65: услуга | E65: 30000 | G65: услуга | H65: =IF(OR(E65="",F65=""),0,E65*F65) | I65: =IF(D65="закупка",H65*'Параметры'!$C$6,0) | J65: =H65+I65
B66: Порошок | C66: Покраска шагрень | D66: услуга | E66: 2300 | G66: услуга | H66: =IF(OR(E66="",F66=""),0,E66*F66) | I66: =IF(D66="закупка",H66*'Параметры'!$C$6,0) | J66: =H66+I66
B67: Порошок | C67: Покраска антик (молотковая) | D67: услуга | E67: 2200 | G67: услуга | H67: =IF(OR(E67="",F67=""),0,E67*F67) | I67: =IF(D67="закупка",H67*'Параметры'!$C$6,0) | J67: =H67+I67
B68: Порошок | C68: Транспорт на покраску | D68: транспорт | E68: 2000 | G68: рейс | H68: =IF(OR(E68="",F68=""),0,E68*F68) | I68: =IF(D68="закупка",H68*'Параметры'!$C$6,0) | J68: =H68+I68
B69: Порошок | C69: Транспорт с покраски | D69: транспорт | E69: 2000 | G69: рейс | H69: =IF(OR(E69="",F69=""),0,E69*F69) | I69: =IF(D69="закупка",H69*'Параметры'!$C$6,0) | J69: =H69+I69
B70: Порошок | C70: Транспорт людей | D70: транспорт | E70: 500 | G70: поездка | H70: =IF(OR(E70="",F70=""),0,E70*F70) | I70: =IF(D70="закупка",H70*'Параметры'!$C$6,0) | J70: =H70+I70
B71: 9. Монтаж
B72: Монтаж | C72: Аренда | D72: аренда | E72: ='Параметры'!$C$10 | G72: день | H72: =IF(OR(E72="",F72=""),0,E72*F72) | I72: =IF(D72="закупка",H72*'Параметры'!$C$6,0) | J72: =H72+I72 | L72: Ставка аренды из Параметры
B73: Монтаж | C73: Монтажники | D73: труд | E73: 5000 | G73: день | H73: =IF(OR(E73="",F73=""),0,E73*F73) | I73: =IF(D73="закупка",H73*'Параметры'!$C$6,0) | J73: =H73+I73
B74: Монтаж | C74: Помощник | D74: труд | E74: 4000 | G74: день | H74: =IF(OR(E74="",F74=""),0,E74*F74) | I74: =IF(D74="закупка",H74*'Параметры'!$C$6,0) | J74: =H74+I74
B75: Монтаж | C75: Крепежи, хим.анкер | D75: закупка | E75: 2000 | G75: набор | H75: =IF(OR(E75="",F75=""),0,E75*F75) | I75: =IF(D75="закупка",H75*'Параметры'!$C$6,0) | J75: =H75+I75
B76: Монтаж | C76: Транспорт рабочих | D76: транспорт | E76: 500 | F76: 0 | G76: поездка | H76: =IF(OR(E76="",F76=""),0,E76*F76) | I76: =IF(D76="закупка",H76*'Параметры'!$C$6,0) | J76: =H76+I76
B77: Монтаж | C77: Транспорт оборудования на объект | D77: транспорт | E77: 2000 | F77: 0 | G77: рейс | H77: =IF(OR(E77="",F77=""),0,E77*F77) | I77: =IF(D77="закупка",H77*'Параметры'!$C$6,0) | J77: =H77+I77
B78: Монтаж | C78: Транспорт оборудования в цех | D78: транспорт | E78: 2000 | F78: 0 | G78: рейс | H78: =IF(OR(E78="",F78=""),0,E78*F78) | I78: =IF(D78="закупка",H78*'Параметры'!$C$6,0) | J78: =H78+I78
B79: 10. Расходники в день
B80: Расходники/день | C80: Абразивы | D80: закупка | E80: 600 | G80: день | H80: =IF(OR(E80="",F80=""),0,E80*F80) | I80: =IF(D80="закупка",H80*'Параметры'!$C$6,0) | J80: =H80+I80
B81: Расходники/день | C81: Кислород | D81: закупка | E81: 330 | F81: 0 | G81: день | H81: =IF(OR(E81="",F81=""),0,E81*F81) | I81: =IF(D81="закупка",H81*'Параметры'!$C$6,0) | J81: =H81+I81 | L81: ориентир: баллон / срок
B82: Расходники/день | C82: Углекислота | D82: закупка | E82: 65 | F82: 0 | G82: день | H82: =IF(OR(E82="",F82=""),0,E82*F82) | I82: =IF(D82="закупка",H82*'Параметры'!$C$6,0) | J82: =H82+I82
B83: Расходники/день | C83: Пропан (газ) | D83: закупка | E83: 690 | G83: день | H83: =IF(OR(E83="",F83=""),0,E83*F83) | I83: =IF(D83="закупка",H83*'Параметры'!$C$6,0) | J83: =H83+I83
B84: Расходники/день | C84: Ковка (уголь) | D84: закупка | E84: 3100 | F84: 0 | G84: день | H84: =IF(OR(E84="",F84=""),0,E84*F84) | I84: =IF(D84="закупка",H84*'Параметры'!$C$6,0) | J84: =H84+I84
B85: Расходники/день | C85: Амортизация инструмента | D85: прочее | E85: 740 | G85: день | H85: =IF(OR(E85="",F85=""),0,E85*F85) | I85: =IF(D85="закупка",H85*'Параметры'!$C$6,0) | J85: =H85+I85
H86: =IF(OR(E86="",F86=""),0,E86*F86) | I86: =IF(D86="закупка",H86*'Параметры'!$C$6,0) | J86: =H86+I86
H87: =IF(OR(E87="",F87=""),0,E87*F87) | I87: =IF(D87="закупка",H87*'Параметры'!$C$6,0) | J87: =H87+I87
B88: 11. Стоимость проектирования
B89: Проектирование | C89: Разработка проекта | D89: труд | E89: 1000 | F89: 1 | G89: час | H89: =IF(OR(E89="",F89=""),0,E89*F89) | I89: =IF(D89="закупка",H89*'Параметры'!$C$6,0) | J89: =H89+I89
B90: Проектирование | C90: Виктор обрисовка под лазерную резку | D90: услуга | E90: 121 | F90: 1 | G90: час | H90: =IF(OR(E90="",F90=""),0,E90*F90) | I90: =IF(D90="закупка",H90*'Параметры'!$C$6,0) | J90: =H90+I90
B91: Проектирование | D91: услуга | H91: =IF(OR(E91="",F91=""),0,E91*F91) | I91: =IF(D91="закупка",H91*'Параметры'!$C$6,0) | J91: =H91+I91
B92: Проектирование | H92: =IF(OR(E92="",F92=""),0,E92*F92) | I92: =IF(D92="закупка",H92*'Параметры'!$C$6,0) | J92: =H92+I92
B93: Проектирование | H93: =IF(OR(E93="",F93=""),0,E93*F93) | I93: =IF(D93="закупка",H93*'Параметры'!$C$6,0) | J93: =H93+I93
B94: Проектирование | H94: =IF(OR(E94="",F94=""),0,E94*F94) | I94: =IF(D94="закупка",H94*'Параметры'!$C$6,0) | J94: =H94+I94
H95: =IF(OR(E95="",F95=""),0,E95*F95) | I95: =IF(D95="закупка",H95*'Параметры'!$C$6,0) | J95: =H95+I95
H96: =IF(OR(E96="",F96=""),0,E96*F96) | I96: =IF(D96="закупка",H96*'Параметры'!$C$6,0) | J96: =H96+I96
H97: =IF(OR(E97="",F97=""),0,E97*F97) | I97: =IF(D97="закупка",H97*'Параметры'!$C$6,0) | J97: =H97+I97
H98: =IF(OR(E98="",F98=""),0,E98*F98) | I98: =IF(D98="закупка",H98*'Параметры'!$C$6,0) | J98: =H98+I98
H99: =IF(OR(E99="",F99=""),0,E99*F99) | I99: =IF(D99="закупка",H99*'Параметры'!$C$6,0) | J99: =H99+I99
H100: =IF(OR(E100="",F100=""),0,E100*F100) | I100: =IF(D100="закупка",H100*'Параметры'!$C$6,0) | J100: =H100+I100
H101: =IF(OR(E101="",F101=""),0,E101*F101) | I101: =IF(D101="закупка",H101*'Параметры'!$C$6,0) | J101: =H101+I101
H102: =IF(OR(E102="",F102=""),0,E102*F102) | I102: =IF(D102="закупка",H102*'Параметры'!$C$6,0) | J102: =H102+I102
...

Sheet Металл
B2: МЕТАЛЛ И КОМПЛЕКТУЮЩИЕ — каталог
B3: Цена поставщика = за 1 шт (штанга 6 м). Кол-во — сколько штанг в заказ. Вес 6м — справочно. Наценка менеджера: себестоимость × % из Параметров.
B4: ПРОКАТ (каталог поставщика)
B5: Прокат | C5: Сечение | D5: Кол-во | E5: Ед. | F5: Цена поставщика, ₽/шт (6м) | G5: С наценкой менеджера | H5: Себестоимость | I5: Наценка менеджера | J5: Вес 6м, кг
B6: Квадрат | C6: 10х10 | E6: шт | F6: 428.3 | G6: =H6*(1+'Параметры'!$C$6) | H6: =IF(OR(D6="",F6=""),0,D6*F6) | I6: =H6*'Параметры'!$C$6 | J6: 5.1
B7: Квадрат | C7: 12х12 | E7: шт | F7: 596.26 | G7: =H7*(1+'Параметры'!$C$6) | H7: =IF(OR(D7="",F7=""),0,D7*F7) | I7: =H7*'Параметры'!$C$6 | J7: 7.1
B8: Квадрат | C8: 14х14 | E8: шт | F8: 797.81 | G8: =H8*(1+'Параметры'!$C$6) | H8: =IF(OR(D8="",F8=""),0,D8*F8) | I8: =H8*'Параметры'!$C$6 | J8: 9.5
B9: Квадрат | C9: 16х16 | E9: шт | F9: 1058.15 | G9: =H9*(1+'Параметры'!$C$6) | H9: =IF(OR(D9="",F9=""),0,D9*F9) | I9: =H9*'Параметры'!$C$6 | J9: 12.6
B10: Труба квадрат. | C10: 15х15х1.5 | E10: шт | F10: 383.8 | G10: =H10*(1+'Параметры'!$C$6) | H10: =IF(OR(D10="",F10=""),0,D10*F10) | I10: =H10*'Параметры'!$C$6 | J10: 4
B11: Труба квадрат. | C11: 20х20х1.5 | E11: шт | F11: 575.7 | G11: =H11*(1+'Параметры'!$C$6) | H11: =IF(OR(D11="",F11=""),0,D11*F11) | I11: =H11*'Параметры'!$C$6 | J11: 6
B12: Труба квадрат. | C12: 20х20х2.0 | E12: шт | F12: 586.53 | G12: =H12*(1+'Параметры'!$C$6) | H12: =IF(OR(D12="",F12=""),0,D12*F12) | I12: =H12*'Параметры'!$C$6 | J12: 7
B13: Труба квадрат. | C13: 30х30х2.0 | E13: шт | F13: 921.69 | G13: =H13*(1+'Параметры'!$C$6) | H13: =IF(OR(D13="",F13=""),0,D13*F13) | I13: =H13*'Параметры'!$C$6 | J13: 11
B14: Труба квадрат. | C14: 40х40х1.5 | E14: шт | F14: 1151.4 | G14: =H14*(1+'Параметры'!$C$6) | H14: =IF(OR(D14="",F14=""),0,D14*F14) | I14: =H14*'Параметры'!$C$6 | J14: 12
B15: Труба квадрат. | C15: 40х40х2.0 | E15: шт | F15: 1256.85 | G15: =H15*(1+'Параметры'!$C$6) | H15: =IF(OR(D15="",F15=""),0,D15*F15) | I15: =H15*'Параметры'!$C$6 | J15: 15
B16: Труба прямоуг. | C16: 40х20х1.5 | E16: шт | F16: 863.55 | G16: =H16*(1+'Параметры'!$C$6) | H16: =IF(OR(D16="",F16=""),0,D16*F16) | I16: =H16*'Параметры'!$C$6 | J16: 9
B17: Труба прямоуг. | C17: 40х20х2.0 | E17: шт | F17: 921.69 | G17: =H17*(1+'Параметры'!$C$6) | H17: =IF(OR(D17="",F17=""),0,D17*F17) | I17: =H17*'Параметры'!$C$6 | J17: 11
... B36: Прокат круглый | C36: Ø16 | E36: шт | F36: 901.7 | G36: =H36*(1+'Параметры'!$C$6) | H36: =IF(OR(D36="",F36=""),0,D36*F36) | I36: =H36*'Параметры'!$C$6 | J36: 10
B37: Итого прокат | F37: Прокат — себестоимость: | G37: =SUM(G6:G36) | H37: =SUM(H6:H36) | I37: =SUM(I6:I36)
B39: ПЛАЗМА / ЛАЗЕР (до 10 позиций)
B41: Позиция | C41: Сечение / описание | D41: Кол-во | E41: Ед. | F41: Цена поставщика | G41: С наценкой менеджера | H41: Себестоимость | I41: Наценка менеджера
D42: 0 | E42: шт | F42: 0 | G42: =H42*(1+'Параметры'!$C$6) | H42: =IF(OR(D42="",F42=""),0,D42*F42) | I42: =H42*'Параметры'!$C$6
D43: 0 | E43: шт | F43: 0 | G43: =H43*(1+'Параметры'!$C$6) | H43: =IF(OR(D43="",F43=""),0,D43*F43) | I43: =H43*'Параметры'!$C$6
D44: 0 | E44: шт | F44: 0 | G44: =H44*(1+'Параметры'!$C$6) | H44: =IF(OR(D44="",F44=""),0,D44*F44) | I44: =H44*'Параметры'!$C$6
D45: 0 | E45: шт | F45: 0 | G45: =H45*(1+'Параметры'!$C$6) | H45: =IF(OR(D45="",F45=""),0,D45*F45) | I45: =H45*'Параметры'!$C$6
D46: 0 | E46: шт | F46: 0 | G46: =H46*(1+'Параметры'!$C$6) | H46: =IF(OR(D46="",F46=""),0,D46*F46) | I46: =H46*'Параметры'!$C$6
D47: 0 | E47: шт | F47: 0 | G47: =H47*(1+'Параметры'!$C$6) | H47: =IF(OR(D47="",F47=""),0,D47*F47) | I47: =H47*'Параметры'!$C$6
D48: 0 | E48: шт | F48: 0 | G48: =H48*(1+'Параметры'!$C$6) | H48: =IF(OR(D48="",F48=""),0,D48*F48) | I48: =H48*'Параметры'!$C$6
D49: 0 | E49: шт | F49: 0 | G49: =H49*(1+'Параметры'!$C$6) | H49: =IF(OR(D49="",F49=""),0,D49*F49) | I49: =H49*'Параметры'!$C$6
D50: 0 | E50: шт | F50: 0 | G50: =H50*(1+'Параметры'!$C$6) | H50: =IF(OR(D50="",F50=""),0,D50*F50) | I50: =H50*'Параметры'!$C$6
D51: 0 | E51: шт | F51: 0 | G51: =H51*(1+'Параметры'!$C$6) | H51: =IF(OR(D51="",F51=""),0,D51*F51) | I51: =H51*'Параметры'!$C$6
F52: ПЛАЗМА / ЛАЗЕР — себестоимость: | G52: =SUM(G42:G51) | H52: =SUM(H42:H51) | I52: =SUM(I42:I51)
B54: КОВАНЫЕ ЭЛЕМЕНТЫ / СПЕЦ. ПРОКАТ (до 10 позиций)
B56: Элемент / артикул | C56: Сечение | D56: Кол-во | E56: Ед. | F56: Цена поставщика | G56: С наценкой менеджера | H56: Себестоимость | I56: Наценка менеджера
B57: Пики | E57: шт | F57: 3200 | G57: =H57*(1+'Параметры'!$C$6) | H57: =IF(OR(D57="",F57=""),0,D57*F57) | I57: =H57*'Параметры'!$C$6
B58: Полоса | E58: шт | F58: 10340 | G58: =H58*(1+'Параметры'!$C$6) | H58: =IF(OR(D58="",F58=""),0,D58*F58) | I58: =H58*'Параметры'!$C$6
B59: шар | E59: шт | F59: 1050 | G59: =H59*(1+'Параметры'!$C$6) | H59: =IF(OR(D59="",F59=""),0,D59*F59) | I59: =H59*'Параметры'!$C$6
E60: шт | F60: 0 | G60: =H60*(1+'Параметры'!$C$6) | H60: =IF(OR(D60="",F60=""),0,D60*F60) | I60: =H60*'Параметры'!$C$6
E61: шт | F61: 0 | G61: =H61*(1+'Параметры'!$C$6) | H61: =IF(OR(D61="",F61=""),0,D61*F61) | I61: =H61*'Параметры'!$C$6
D62: 0 | E62: шт | F62: 0 | G62: =H62*(1+'Параметры'!$C$6) | H62: =IF(OR(D62="",F62=""),0,D62*F62) | I62: =H62*'Параметры'!$C$6
D63: 0 | E63: шт | F63: 0 | G63: =H63*(1+'Параметры'!$C$6) | H63: =IF(OR(D63="",F63=""),0,D63*F63) | I63: =H63*'Параметры'!$C$6
D64: 0 | E64: шт | F64: 0 | G64: =H64*(1+'Параметры'!$C$6) | H64: =IF(OR(D64="",F64=""),0,D64*F64) | I64: =H64*'Параметры'!$C$6
D65: 0 | E65: шт | F65: 0 | G65: =H65*(1+'Параметры'!$C$6) | H65: =IF(OR(D65="",F65=""),0,D65*F65) | I65: =H65*'Параметры'!$C$6
D66: 0 | E66: шт | F66: 0 | G66: =H66*(1+'Параметры'!$C$6) | H66: =IF(OR(D66="",F66=""),0,D66*F66) | I66: =H66*'Параметры'!$C$6
F67: КОВАНЫЕ ЭЛЕМЕНТЫ / СПЕЦ. ПРОКАТ — себестоимость: | G67: =SUM(G57:G66) | H67: =SUM(H57:H66) | I67: =SUM(I57:I66)
B69: ТОКАРНЫЕ РАБОТЫ (до 10 позиций)
B71: Позиция | C71: Сечение / описание | D71: Кол-во | E71: Ед. | F71: Цена поставщика | G71: С наценкой менеджера | H71: Себестоимость | I71: Наценка менеджера
D72: 0 | E72: шт | F72: 0 | G72: =H72*(1+'Параметры'!$C$6) | H72: =IF(OR(D72="",F72=""),0,D72*F72) | I72: =H72*'Параметры'!$C$6
D73: 0 | E73: шт | F73: 0 | G73: =H73*(1+'Параметры'!$C$6) | H73: =IF(OR(D73="",F73=""),0,D73*F73) | I73: =H73*'Параметры'!$C$6
D74: 0 | E74: шт | F74: 0 | G74: =H74*(1+'Параметры'!$C$6) | H74: =IF(OR(D74="",F74=""),0,D74*F74) | I74: =H74*'Параметры'!$C$6
D75: 0 | E75: шт | F75: 0 | G75: =H75*(1+'Параметры'!$C$6) | H75: =IF(OR(D75="",F75=""),0,D75*F75) | I75: =H75*'Параметры'!$C$6
D76: 0 | E76: шт | F76: 0 | G76: =H76*(1+'Параметры'!$C$6) | H76: =IF(OR(D76="",F76=""),0,D76*F76) | I76: =H76*'Параметры'!$C$6
D77: 0 | E77: шт | F77: 0 | G77: =H77*(1+'Параметры'!$C$6) | H77: =IF(OR(D77="",F77=""),0,D77*F77) | I77: =H77*'Параметры'!$C$6
D78: 0 | E78: шт | F78: 0 | G78: =H78*(1+'Параметры'!$C$6) | H78: =IF(OR(D78="",F78=""),0,D78*F78) | I78: =H78*'Параметры'!$C$6
D79: 0 | E79: шт | F79: 0 | G79: =H79*(1+'Параметры'!$C$6) | H79: =IF(OR(D79="",F79=""),0,D79*F79) | I79: =H79*'Параметры'!$C$6
D80: 0 | E80: шт | F80: 0 | G80: =H80*(1+'Параметры'!$C$6) | H80: =IF(OR(D80="",F80=""),0,D80*F80) | I80: =H80*'Параметры'!$C$6
D81: 0 | E81: шт | F81: 0 | G81: =H81*(1+'Параметры'!$C$6) | H81: =IF(OR(D81="",F81=""),0,D81*F81) | I81: =H81*'Параметры'!$C$6
F82: ТОКАРНЫЕ РАБОТЫ — себестоимость: | G82: =SUM(G72:G81) | H82: =SUM(H72:H81) | I82: =SUM(I72:I81)
B84: ДОПОЛНИТЕЛЬНЫЕ КОМПЛЕКТУЮЩИЕ (до 10 позиций)
B86: Комплектующая | C86: Описание / артикул | D86: Кол-во | E86: Ед. | F86: Цена поставщика | G86: С наценкой менеджера | H86: Себестоимость | I86: Наценка менеджера
B87: Петли | E87: шт | F87: 0 | G87: =H87*(1+'Параметры'!$C$6) | H87: =IF(OR(D87="",F87=""),0,D87*F87) | I87: =H87*'Параметры'!$C$6
B88: ЗАмок | E88: шт | F88: 0 | G88: =H88*(1+'Параметры'!$C$6) | H88: =IF(OR(D88="",F88=""),0,D88*F88) | I88: =H88*'Параметры'!$C$6
E89: шт | F89: 0 | G89: =H89*(1+'Параметры'!$C$6) | H89: =IF(OR(D89="",F89=""),0,D89*F89) | I89: =H89*'Параметры'!$C$6
D90: 0 | E90: шт | F90: 0 | G90: =H90*(1+'Параметры'!$C$6) | H90: =IF(OR(D90="",F90=""),0,D90*F90) | I90: =H90*'Параметры'!$C$6
D91: 0 | E91: шт | F91: 0 | G91: =H91*(1+'Параметры'!$C$6) | H91: =IF(OR(D91="",F91=""),0,D91*F91) | I91: =H91*'Параметры'!$C$6
D92: 0 | E92: шт | F92: 0 | G92: =H92*(1+'Параметры'!$C$6) | H92: =IF(OR(D92="",F92=""),0,D92*F92) | I92: =H92*'Параметры'!$C$6
D93: 0 | E93: шт | F93: 0 | G93: =H93*(1+'Параметры'!$C$6) | H93: =IF(OR(D93="",F93=""),0,D93*F93) | I93: =H93*'Параметры'!$C$6
D94: 0 | E94: шт | F94: 0 | G94: =H94*(1+'Параметры'!$C$6) | H94: =IF(OR(D94="",F94=""),0,D94*F94) | I94: =H94*'Параметры'!$C$6
D95: 0 | E95: шт | F95: 0 | G95: =H95*(1+'Параметры'!$C$6) | H95: =IF(OR(D95="",F95=""),0,D95*F95) | I95: =H95*'Параметры'!$C$6
D96: 0 | E96: шт | F96: 0 | G96: =H96*(1+'Параметры'!$C$6) | H96: =IF(OR(D96="",F96=""),0,D96*F96) | I96: =H96*'Параметры'!$C$6
F97: ДОПОЛНИТЕЛЬНЫЕ КОМПЛЕКТУЮЩИЕ — себестоимость: | G97: =SUM(G87:G96) | H97: =SUM(H87:H96) | I97: =SUM(I87:I96)
F99: ВСЕГО металл — себестоимость: | H99: =H37+H52+H67+H82+H97
F100: ВСЕГО наценка менеджера с листа Металл: | H100: =I37+I52+I67+I82+I97
B102: Обновление прайса: меняйте жёлтые цены в колонке F. Кол-во D — под заказ. Прокат, плазма, ковка, токарка и комплектующие — с наценкой менеджера. Итоги уходят в Калькуляцию автоматически.

Sheet Предложение
B1: ЛЕНДИНГ-КП ДЛЯ PDF (стиль Cenzyk). Цена — со Сводки. Жёлтые доли раскладывают Итого. Экспорт: Файл → PDF. | F1: Цена КП: | G1: ='Сводка'!D24
B3: =UPPER('Параметры'!C23)&" · КП" | D3: № | E3: =IF('Сводка'!C11="","—",'Сводка'!C11)
B4: ='Параметры'!C19
B6: ='Параметры'!C20
B7: ИЗДЕЛИЯ ИЗ МЕТАЛЛА · КАЛИНИНГРАД И ОБЛАСТЬ
B9: КЛИЕНТ | C9: ='Сводка'!C10 | E9: ОБЪЕКТ | F9: ='Сводка'!C6
B10: ДАТА | C10: ='Сводка'!C9 | E10: АКТУАЛЬНО ДО | F10: =C10+'Параметры'!C31
B12: 01 / ВИЗУАЛИЗАЦИЯ | D12: РЕКОМЕНДУЕМОЕ РАЗРЕШЕНИЕ: 1024×1024 px (квадрат)
B13: РАКУРС 1 · ФРОНТ | D13: РАКУРС 2 · 3/4 | E13: РАКУРС 3 · СБОКУ
B14: Вставка → Изображение 1024×1024 | D14: Вставка → Изображение 1024×1024 | E14: Вставка → Изображение 1024×1024
B22: Три ракурса одного изделия. Формат JPG/PNG, без сжатия «для веба». Допустимо 1200×1200.
B24: 02 / ИЗДЕЛИЕ
B25: ='Сводка'!C7
B27: ="Тип: "&'Сводка'!C8
B29: 03 / СОСТАВ РАБОТ
B30: 01 | C30: Проектирование и подготовка | E30: 0.05 | F30: =IF('Сводка'!$D$24=0,0,ROUND('Сводка'!$D$24*E30,2))
C31: замер, эскизы, лекала
B32: 02 | C32: Материалы | E32: 0.35 | F32: =IF('Сводка'!$D$24=0,0,ROUND('Сводка'!$D$24*E32,2))
C33: металл, комплектующие, резка / токарка
B34: 03 | C34: Изготовление | E34: 0.35 | F34: =IF('Сводка'!$D$24=0,0,ROUND('Сводка'!$D$24*E34,2))
C35: цех, сварка, расходники
B36: 04 | C36: Окраска и обработка | E36: 0.1 | F36: =IF('Сводка'!$D$24=0,0,ROUND('Сводка'!$D$24*E36,2))
C37: эмаль / порошок / пескоструй
B38: 05 | C38: Монтаж / доставка | E38: 0.15 | F38: =IF('Сводка'!$D$24=0,0,ROUND('Сводка'!$D$24*E38,2))
C39: доставка на объект, установка
B41: ДОЛИ | E41: =SUM(E30,E32,E34,E36,E38) | F41: =IF(ABS(E41-1)<0.001,"OK","проверьте доли")
B43: ИТОГО | E43: =F30+F32+F34+F36+F38
B45: СВОДКА | E45: ='Сводка'!D24 | F45: =IF('Сводка'!D24=0,"введите цену КП",IF(ABS(E43-'Сводка'!D24)<1,"сходится","расходится"))
B47: ПРОВЕДЕНИЕ ЧЕРЕЗ СЗ 4% · ФИЗ. ЛИЦО | F47: =E43*1.04
B48: ПРОВЕДЕНИЕ ЧЕРЕЗ СЗ 6% · ЮР. ЛИЦО | F48: =E43*1.06
B50: 04 / УСЛОВИЯ
B51: АВАНС | D51: 0.5 | F51: =E43*D51
B52: ОСТАТОК | F52: =E43-F51
B53: СРОК | D53: 14–21 рабочий день
B55: 05 / КОНТАКТЫ
B56: ='Параметры'!C19 | D56: ='Параметры'!C20
B57: ="Т "&'Параметры'!C22 | D57: ="Пн–Пт "&'Параметры'!C26
B58: ="W "&'Параметры'!C23 | D58: ="Сб "&'Параметры'!C27&" Вс "&'Параметры'!C28
B59: ="E "&'Параметры'!C24 | D59: ='Параметры'!C30
B60: ="A "&'Параметры'!C25
B61: ="ДЕЙСТВИТЕЛЬНО ДО "&TEXT(F10,"DD.MM.YYYY")

Sheet Параметры
B2: ПАРАМЕТРЫ РАСЧЁТА
B3: Меняйте только жёлтые ячейки. Все калькуляции подтягивают значения отсюда.
B5: Параметр | C5: Значение | D5: Комментарий
B6: Наценка менеджера на закупки | C6: 0.15 | D6: От цены поставщика. Ваша прибыль как менеджера.
B7: Целевая маржа проекта (от выручки) | C7: 0.2 | D7: Чистая маржа после НПД. Диапазон обычно 10%…30%+.
B8: Минимальная допустимая маржа | C8: 0.1 | D8: Ниже — статус «НИЖЕ МИНИМУМА».
B9: Налог НПД (самозанятость) | C9: 0.04 | D9: 4% — физлица, 6% — юрлица/ИП.
B10: Аренда, ₽ / рабочий день | C10: 2000 | D10: Ставка аренды цеха на рабочий день.
B11: Рабочих дней в месяце | C11: 22 | D11: Справочно для пересчёта постоянных расходов.
B12: Агентские, % от цены КП | C12: 0 | D12: Если есть посредник — поставьте %, иначе 0.
B14: Авто-коэффициенты
B15: Множитель цены при целевой марже | C15: =1/(1-C9-C7-C12) | D15: Цена КП ≈ Себестоимость × коэффициент
B16: Множитель цены при минимальной марже | C16: =1/(1-C9-C8-C12)
B18: БРЕНД И КОНТАКТЫ ДЛЯ КП
B19: Имя в шапке КП | C19: Илай Саматов
B20: Подзаголовок | C20: Дизайн / Проектирование / Производство
B21: ФИО полностью | C21: Самозанятый Саматов Илай Валерьевич
B22: Телефон | C22: +7 (952) 058-92-78
B23: Сайт | C23: Cenzyk.art
B24: Email | C24: ilja.samatov@yandex.ru
B25: Адрес | C25: г. Калининград, ул. Ручейная, 2а
B26: График Пн–Пт | C26: 9:00-17:00
B27: График Сб | C27: 10:00-14:00
B28: График Вс | C28: выходной
B29: Стаж | C29: 11 лет
B30: Профиль (текст) | C30: Изделия из металла под ключ: балконы, заборы, лестницы, мебель.
B31: Срок действия КП, дней | C31: 10
B33: Тип изделия (список для шапки)
B34: Ворота
B35: Забор
B36: Лестница
B37: Мебель
B38: Интерьер
B39: Экстерьер
B40: Сувенир
B41: Прочее
B43: Правило маржи
B44: Себестоимость C = реальные выплаты (материалы по цене поставщика, труд, транспорт, аренда, расходники, субподряд). Наценка менеджера = % только на тип «закупка» — это часть вашей прибыли, не расход. Цена для целевой маржи P = C / (1 − НПД% − целевая маржа% − агентские%). Прибыль = P − C − P×НПД − P×агентские. Маржа % = Прибыль / P. В листе «Предложение» варианты СЗ 4%/6% считаются как Итого×1.04 / Итого×1.06 — как в вашем PDF. КАССА — опциональный учёт денег после сделки, на цену КП не влияет.

Sheet Касса
B2: КАССА ЗАКАЗА — опционально (после сделки)
B3: ЭТОТ ЛИСТ НЕ УЧАСТВУЕТ В РАСЧЁТЕ ЦЕНЫ И МАРЖИ. Нужен только чтобы помнить: сколько клиент уже заплатил и сколько вы уже потратили по заказу. Если считаете только КП — этот лист можно полностью игнорировать. Связь со Сводкой: одна — подтягивает «Цену КП» (сколько договорились), чтобы показать остаток к получению. Обратно в Сводку / Калькуляцию / Металл касса НИЧЕГО не отправляет.
B9: 1) СКОЛЬКО ПОЛУЧИЛИ ОТ КЛИЕНТА
B10: Дата | C10: Что за платёж | D10: Сумма
C16: Всего получено: | D16: =SUM(D11:D15)
C17: Цена КП (из Сводки, только для справки): | D17: ='Сводка'!D24
C18: Ещё должен клиент: | D18: =D17-D16
B20: 2) СКОЛЬКО УЖЕ ВЫПЛАТИЛИ ПО ЗАКАЗУ
B21: Дата | C21: Кому / за что | D21: Сумма
C43: Всего выплат: | D43: =SUM(D22:D41)
C44: Живые деньги по заказу сейчас (получено − выплаты): | D44: =D16-D43
B46: Пример: КП 100 000, аванс 50 000, купили металл 20 000 → получено 50 000, выплат 20 000, в кассе заказа 30 000. Прибыль при этом смотрите на Сводке, не здесь.

Sheet Инструкция
B2: Как работать с файлом
B4: ГЛАВНЫЙ КОНТУР (для цены КП):
B5: 1. «Параметры» — % менеджера, целевая/мин. маржа, НПД, аренда/день, бренд/контакты.
B6: 2. «Металл» — кол-во штанг проката (шт = 6 м), плюс плазма/ковка/токарка/комплектующие. На все эти блоки — наценка менеджера.
B7: 3. «Калькуляция» — количества по этапам (дни, рейсы, материалы).
B8: 4. «Сводка» — смотрите рекомендуемую цену, впишите Цену КП в жёлтую ячейку, проверьте статус.
B9: 5. «Предложение» — лендинг-КП в стиле Cenzyk: hero, фото, 5 блоков, жёлтый ИТОГО, СЗ, условия, контакты.
B11: КАК ОТПРАВИТЬ КЛИЕНТУ (не скриншот Excel):
B12: • На «Предложении» проверьте доли (итог 100%) и статус «сходится» со Сводкой.
B13: • Вставьте 3 ракурса 1024×1024 (фронт / 3⁄4 / сбоку) на «Предложении».
B14: • Файл → Экспорт → Создать PDF/XPS (или Печать → Microsoft Print to PDF) — только лист «Предложение».
B15: • В WhatsApp / почту: PDF + 2–4 картинки рендеров (папки «под предложение 1024×1024»).
... B23: В шапке Сводки: Клиент + № клиента.
